turbopower/__init__.py
turbopower/matematicas.py
turbopower-0.1.0.dist-info/METADATA
turbopower-0.1.0.dist-info/WHEEL
turbopower-0.1.0.dist-info/RECORD
