Metadata-Version: 2.1
Name: turbopower
Version: 0.1.0
Summary: Paquete de tuberias
Home-page: https://github.com/….
Author: Steven
Author-email: ssmedina2@utpl.edu.ec
Requires-Python: >=3.10.0,<3.12
Classifier: Programming Language :: Python :: 3
Classifier: Programming Language :: Python :: 3.10
Classifier: Programming Language :: Python :: 3.11
Project-URL: Repository, https://github.com/….
Project-URL: repository, https://github.com/…
